mgpustat/__init__.py
mgpustat/main.py
mgpustat-0.1.0.dist-info/LICENSE
mgpustat-0.1.0.dist-info/METADATA
mgpustat-0.1.0.dist-info/WHEEL
mgpustat-0.1.0.dist-info/entry_points.txt
mgpustat-0.1.0.dist-info/top_level.txt
mgpustat-0.1.0.dist-info/RECORD
