Metadata-Version: 2.1
Name: mgpustat
Version: 0.1.0
Summary: A GPU statistics utility for Apple Silicon Macs.
Home-page: https://github.com/rathull/mgpustat
Author: Rathul Anand
Author-email: notifyrathul@gmail.com
Classifier: Development Status :: 3 - Alpha
Classifier: Intended Audience :: Developers
Classifier: License :: OSI Approved :: MIT License
Classifier: Operating System :: MacOS :: MacOS X
Classifier: Programming Language :: Python :: 3
Classifier: Programming Language :: Python :: 3.7
Classifier: Programming Language :: Python :: 3.8
Classifier: Programming Language :: Python :: 3.9
Requires-Python: >=3.7
License-File: LICENSE
Requires-Dist: rich
